hukudo/__init__.py
hukudo/chromedriver.py
hukudo/cli.py
hukudo/exc.py
hukudo/filesystem.py
hukudo/log.py
hukudo/gitlab/__init__.py
hukudo/gitlab/api.py
hukudo/gitlab/cli.py
hukudo/gitlab/config.py
hukudo/gitlab/jobs.py
hukudo/grafana/__init__.py
hukudo/grafana/api.py
hukudo/grafana/cli.py
hukudo/grafana/demo.py
hukudo/grafana/errors.py
hukudo/grafana/models.py
hukudo/pypi/__init__.py
hukudo/pypi/cli.py
hukudo/xls/__init__.py
hukudo/xls/edi.py
hukudo/xls/fmt.py
hukudo/xls/sheet.py
hukudo/xls/table.py
hukudo-3.7.1.dist-info/LICENSE
hukudo-3.7.1.dist-info/METADATA
hukudo-3.7.1.dist-info/WHEEL
hukudo-3.7.1.dist-info/entry_points.txt
hukudo-3.7.1.dist-info/top_level.txt
hukudo-3.7.1.dist-info/RECORD
